rtl/shiftreg.sv
module shiftreg (
    input logic clk,
    input logic rst,
    input logic en, 
    input logic sin, 
    output logic [3:0] sout
);

    always_ff @(posedge clk or posedge rst) begin
        if(rst) begin
            sout <= '0;
        end
        else begin 
            if(en) begin
                sout[0] <= sin;
                sout[1] <= sout[0];
                sout[2] <= sout[1];
                sout[3] <= sout[2];
            end
        end
    end

endmodule : shiftreg

tb/tb_shiftreg.sv

module tb_shiftreg();
    
    logic clk, rst, en, sin; 
    logic [3:0] sout; 
    
 shiftreg dut (
    .clk(clk),
    .rst(rst),
    .en(en), 
    .sin(sin), 
    .sout(sout)
);
    initial begin 
        clk = 0;
        rst = 0; 
        en = 0; 
        forever #10 clk = ~clk; 
    end

    initial begin 
        $dumpvars(0); 
        $dumpfile("tb_shiftreg.vcd");
    end

   initial begin 
       rst = 1; 
       #10; 
       rst = 0; 
       en = 1; 
       repeat(50) begin 
           sin = $urandom_range(0, 2**3-1); 
           #10; 
       end
       $finish; 
   end

endmodule : tb_shiftreg

tb/tb_shiftreg.vcd
$date
	Mon Apr 21 13:36:56 2025
$end

$version
	Synopsys VCS version U-2023.03-SP2-8
$end

$timescale
	1ns
$end

$comment Csum: 1 abd79efa3d2d2c71 $end


$scope module tb_shiftreg $end
$var reg 1 ! clk $end
$var reg 1 " rst $end
$var reg 1 # en $end
$var reg 1 $ sin $end
$var reg 4 % sout [3:0] $end

$scope begin unnamed$$_vcs_0 $end
$upscope $end


$scope module dut $end
$var reg 1 ! clk $end
$var reg 1 " rst $end
$var reg 1 # en $end
$var reg 1 $ sin $end
$var reg 4 % sout [3:0] $end
$upscope $end

$upscope $end

$enddefinitions $end

#0
$dumpvars
0!
0#
1"
x$
b0000 %
$end
#10
1!
0"
1#
1$
b0001 %
#20
0!
#30
1!
0$
b0010 %
#40
0!
1$
#50
1!
b0101 %
#60
0!
#70
1!
b1011 %
#80
0!
0$
#90
1!
1$
b0111 %
#100
0!
0$
#110
1!
1$
b1111 %
#120
0!
#130
1!
0$
b1110 %
#140
0!
1$
#150
1!
0$
b1100 %
#160
0!
1$
#170
1!
0$
b1000 %
#180
0!
1$
#190
1!
b0001 %
#200
0!
#210
1!
b0011 %
#220
0!
#230
1!
0$
b0110 %
#240
0!
#250
1!
1$
b1101 %
#260
0!
0$
#270
1!
b1010 %
#280
0!
#290
1!
1$
b0101 %
#300
0!
#310
1!
0$
b1010 %
#320
0!
#330
1!
b0100 %
#340
0!
1$
#350
1!
b1001 %
#360
0!
#370
1!
b0011 %
#380
0!
0$
#390
1!
1$
b0111 %
#400
0!
#410
1!
b1111 %
#420
0!
0$
#430
1!
1$
#440
0!
#450
1!
0$
b1110 %
#460
0!
1$
#470
1!
0$
b1100 %
#480
0!
1$
#490
1!
0$
b1000 %
